segment_tree/DualSegmentTree.py
segment_tree/SegmentTree.py
segment_tree/TreeNode.py
segment_tree/__init__.py
seg_tree-0.1.dist-info/LICENSE
seg_tree-0.1.dist-info/METADATA
seg_tree-0.1.dist-info/WHEEL
seg_tree-0.1.dist-info/top_level.txt
seg_tree-0.1.dist-info/RECORD
