Metadata-Version: 2.1
Name: seg-tree
Version: 0.1
Summary: A generic segment tree and dual segment tree
Author-email: Yuval Jacoby <jacobyyyuval@gmail.com>
License: MIT License        
Project-URL: Homepage, https://github.com/jyuv/segment-tree
Keywords: data structure,segment,tree,graphs,interval,range,query
Classifier: License :: OSI Approved :: MIT License
Classifier: Programming Language :: Python
Classifier: Programming Language :: Python :: 3
Requires-Python: >=3
License-File: LICENSE
Provides-Extra: dev
Requires-Dist: black ; extra == 'dev'
Requires-Dist: pytest ; extra == 'dev'
